mipscripts/__init__.py
mipscripts/__main__.py
mipscripts/merge_sampleset.py
mipscripts/merge_sampleset_write_fastq.py
mipscripts/seqrun_stats.py
mipscripts/utils.py
mipscripts-0.3.4.dist-info/LICENSE
mipscripts-0.3.4.dist-info/METADATA
mipscripts-0.3.4.dist-info/WHEEL
mipscripts-0.3.4.dist-info/top_level.txt
mipscripts-0.3.4.dist-info/RECORD
