Metadata-Version: 2.1
Name: mipscripts
Version: 0.3.4
Summary: Various tools for use with MIPTools pipelines.
Home-page: https://github.com/bailey-lab/mipscripts
Author: Bailey Lab
Author-email: isaac_kim@brown.edu
Project-URL: Bug Tracker, https://github.com/bailey-lab/mipscripts/issues
Classifier: Programming Language :: Python :: 3
Classifier: License :: OSI Approved :: MIT License
Classifier: Operating System :: OS Independent
Requires-Python: >=3.6
License-File: LICENSE
Requires-Dist: argparse
Requires-Dist: statistics
Requires-Dist: alive-progress
Requires-Dist: pandas
Provides-Extra: test
Requires-Dist: pytest ; extra == 'test'
Requires-Dist: snapshottest ; extra == 'test'
